omero_signup/__init__.py
omero_signup/apps.py
omero_signup/forms.py
omero_signup/signup_settings.py
omero_signup/urls.py
omero_signup/views.py
omero_signup/static/signup/css/ome.signup.css
omero_signup/templates/signup/acknowledge.html
omero_signup/templates/signup/index.html
omero_signup-0.3.3.dist-info/LICENSE
omero_signup-0.3.3.dist-info/METADATA
omero_signup-0.3.3.dist-info/WHEEL
omero_signup-0.3.3.dist-info/top_level.txt
omero_signup-0.3.3.dist-info/RECORD
