Metadata-Version: 2.1
Name: omero-signup
Version: 0.3.3
Summary: A Python plugin for OMERO.web
Home-page: https://github.com/ome/omero-signup
Author: The Open Microscopy Team
Author-email: ome-devel@lists.openmicroscopy.org.uk
License: AGPL-3.0
Download-URL: https://github.com/ome/omero-signup/archive/v0.3.3.tar.gz
Keywords: OMERO.web,plugin
Platform: UNKNOWN
Classifier: Environment :: Web Environment
Classifier: Framework :: Django
Classifier: Intended Audience :: Developers
Classifier: Natural Language :: English
Classifier: Operating System :: OS Independent
Classifier: Programming Language :: Python :: 3
Classifier: Topic :: Internet :: WWW/HTTP
Classifier: Topic :: Internet :: WWW/HTTP :: Dynamic Content
Classifier: Topic :: Internet :: WWW/HTTP :: WSGI
Requires-Python: >=3
License-File: LICENSE
Requires-Dist: omero-web (>=5.6.0)
